cmanager
