Metadata-Version: 1.1
Name: cmanager
Version: 2.2
Summary: CLI (Command Line Interface) for DracOS Linux's users to manage their connection ex: wifi connection.
Home-page: https://github.com/fachrioktavian/CManager/
Author: Fachrizal Oktavian
Author-email: fachri0510@gmail.com
License: GPLv3
Download-URL: https://github.com/fachrioktavian/CManager/tarball/2.2
Keywords: cmanager,dracos connection manager,connection manager
Platform: Linux
Classifier: Development Status :: 5 - Production/Stable
Classifier: License :: OSI Approved :: GNU General Public License v3 (GPLv3)
Classifier: Operating System :: POSIX :: Linux
Classifier: Intended Audience :: Developers
Classifier: Intended Audience :: End Users/Desktop
Classifier: Programming Language :: Python :: 2
Classifier: Programming Language :: Python :: 2.6
Classifier: Programming Language :: Python :: 2.7
Classifier: Programming Language :: Python :: 3
Classifier: Programming Language :: Python :: 3.3
Classifier: Programming Language :: Python :: 3.5
Classifier: Topic :: System :: Networking
Classifier: Topic :: Internet
Classifier: Topic :: Utilities
